{
  "type": "Program",
  "body": [
    {
      "type": "ImportDeclaration",
      "specifiers": [
        {
          "type": "ImportSpecifier",
          "local": {
            "type": "Identifier",
            "name": "Feature",
            "range": [
              9,
              16
            ],
            "loc": {
              "start": {
                "line": 1,
                "column": 9
              },
              "end": {
                "line": 1,
                "column": 16
              }
            }
          },
          "imported": {
            "type": "Identifier",
            "name": "Feature",
            "range": [
              9,
              16
            ],
            "loc": {
              "start": {
                "line": 1,
                "column": 9
              },
              "end": {
                "line": 1,
                "column": 16
              }
            }
          },
          "range": [
            9,
            16
          ],
          "loc": {
            "start": {
              "line": 1,
              "column": 9
            },
            "end": {
              "line": 1,
              "column": 16
            }
          }
        }
      ],
      "source": {
        "type": "Literal",
        "value": "./feature.js",
        "raw": "\"./feature.js\"",
        "range": [
          24,
          38
        ],
        "loc": {
          "start": {
            "line": 1,
            "column": 24
          },
          "end": {
            "line": 1,
            "column": 38
          }
        }
      },
      "range": [
        0,
        39
      ],
      "loc": {
        "start": {
          "line": 1,
          "column": 0
        },
        "end": {
          "line": 1,
          "column": 39
        }
      },
      "trailingComments": [
        {
          "type": "Block",
          "value": "*\r\n * The Typed Array feature.\r\n ",
          "range": [
            43,
            80
          ],
          "loc": {
            "start": {
              "line": 3,
              "column": 0
            },
            "end": {
              "line": 5,
              "column": 3
            }
          }
        }
      ]
    },
    {
      "type": "ExportNamedDeclaration",
      "declaration": {
        "type": "ClassDeclaration",
        "id": {
          "type": "Identifier",
          "name": "TypedArrayFeature",
          "range": [
            97,
            114
          ],
          "loc": {
            "start": {
              "line": 7,
              "column": 13
            },
            "end": {
              "line": 7,
              "column": 30
            }
          }
        },
        "superClass": {
          "type": "Identifier",
          "name": "Feature",
          "range": [
            123,
            130
          ],
          "loc": {
            "start": {
              "line": 7,
              "column": 39
            },
            "end": {
              "line": 7,
              "column": 46
            }
          }
        },
        "body": {
          "type": "ClassBody",
          "body": [
            {
              "type": "MethodDefinition",
              "key": {
                "type": "Identifier",
                "name": "constructor",
                "range": [
                  194,
                  205
                ],
                "loc": {
                  "start": {
                    "line": 13,
                    "column": 1
                  },
                  "end": {
                    "line": 13,
                    "column": 12
                  }
                }
              },
              "value": {
                "type": "FunctionExpression",
                "id": null,
                "params": [],
                "body": {
                  "type": "BlockStatement",
                  "body": [
                    {
                      "type": "ExpressionStatement",
                      "expression": {
                        "type": "CallExpression",
                        "callee": {
                          "type": "Super",
                          "range": [
                            215,
                            220
                          ],
                          "loc": {
                            "start": {
                              "line": 15,
                              "column": 2
                            },
                            "end": {
                              "line": 15,
                              "column": 7
                            }
                          }
                        },
                        "arguments": [
                          {
                            "type": "Literal",
                            "value": "Typed Array",
                            "raw": "\"Typed Array\"",
                            "range": [
                              221,
                              234
                            ],
                            "loc": {
                              "start": {
                                "line": 15,
                                "column": 8
                              },
                              "end": {
                                "line": 15,
                                "column": 21
                              }
                            }
                          }
                        ],
                        "range": [
                          215,
                          235
                        ],
                        "loc": {
                          "start": {
                            "line": 15,
                            "column": 2
                          },
                          "end": {
                            "line": 15,
                            "column": 22
                          }
                        }
                      },
                      "range": [
                        215,
                        236
                      ],
                      "loc": {
                        "start": {
                          "line": 15,
                          "column": 2
                        },
                        "end": {
                          "line": 15,
                          "column": 23
                        }
                      },
                      "trailingComments": [
                        {
                          "type": "Block",
                          "value": "*\r\n\t\t * Indicates whether the Typed Array feature is supported.\r\n\t\t *\r\n\t\t * @type {Boolean}\r\n\t\t ",
                          "range": [
                            242,
                            342
                          ],
                          "loc": {
                            "start": {
                              "line": 17,
                              "column": 2
                            },
                            "end": {
                              "line": 21,
                              "column": 5
                            }
                          }
                        }
                      ]
                    },
                    {
                      "type": "ExpressionStatement",
                      "expression": {
                        "type": "AssignmentExpression",
                        "operator": "=",
                        "left": {
                          "type": "MemberExpression",
                          "computed": false,
                          "object": {
                            "type": "ThisExpression",
                            "range": [
                              348,
                              352
                            ],
                            "loc": {
                              "start": {
                                "line": 23,
                                "column": 2
                              },
                              "end": {
                                "line": 23,
                                "column": 6
                              }
                            }
                          },
                          "property": {
                            "type": "Identifier",
                            "name": "supported",
                            "range": [
                              353,
                              362
                            ],
                            "loc": {
                              "start": {
                                "line": 23,
                                "column": 7
                              },
                              "end": {
                                "line": 23,
                                "column": 16
                              }
                            }
                          },
                          "range": [
                            348,
                            362
                          ],
                          "loc": {
                            "start": {
                              "line": 23,
                              "column": 2
                            },
                            "end": {
                              "line": 23,
                              "column": 16
                            }
                          }
                        },
                        "right": {
                          "type": "BinaryExpression",
                          "operator": "!==",
                          "left": {
                            "type": "MemberExpression",
                            "computed": false,
                            "object": {
                              "type": "MemberExpression",
                              "computed": false,
                              "object": {
                                "type": "ThisExpression",
                                "range": [
                                  366,
                                  370
                                ],
                                "loc": {
                                  "start": {
                                    "line": 23,
                                    "column": 20
                                  },
                                  "end": {
                                    "line": 23,
                                    "column": 24
                                  }
                                }
                              },
                              "property": {
                                "type": "Identifier",
                                "name": "root",
                                "range": [
                                  371,
                                  375
                                ],
                                "loc": {
                                  "start": {
                                    "line": 23,
                                    "column": 25
                                  },
                                  "end": {
                                    "line": 23,
                                    "column": 29
                                  }
                                }
                              },
                              "range": [
                                366,
                                375
                              ],
                              "loc": {
                                "start": {
                                  "line": 23,
                                  "column": 20
                                },
                                "end": {
                                  "line": 23,
                                  "column": 29
                                }
                              }
                            },
                            "property": {
                              "type": "Identifier",
                              "name": "ArrayBuffer",
                              "range": [
                                376,
                                387
                              ],
                              "loc": {
                                "start": {
                                  "line": 23,
                                  "column": 30
                                },
                                "end": {
                                  "line": 23,
                                  "column": 41
                                }
                              }
                            },
                            "range": [
                              366,
                              387
                            ],
                            "loc": {
                              "start": {
                                "line": 23,
                                "column": 20
                              },
                              "end": {
                                "line": 23,
                                "column": 41
                              }
                            }
                          },
                          "right": {
                            "type": "Identifier",
                            "name": "undefined",
                            "range": [
                              392,
                              401
                            ],
                            "loc": {
                              "start": {
                                "line": 23,
                                "column": 46
                              },
                              "end": {
                                "line": 23,
                                "column": 55
                              }
                            }
                          },
                          "range": [
                            366,
                            401
                          ],
                          "loc": {
                            "start": {
                              "line": 23,
                              "column": 20
                            },
                            "end": {
                              "line": 23,
                              "column": 55
                            }
                          }
                        },
                        "range": [
                          348,
                          402
                        ],
                        "loc": {
                          "start": {
                            "line": 23,
                            "column": 2
                          },
                          "end": {
                            "line": 23,
                            "column": 56
                          }
                        }
                      },
                      "range": [
                        348,
                        403
                      ],
                      "loc": {
                        "start": {
                          "line": 23,
                          "column": 2
                        },
                        "end": {
                          "line": 23,
                          "column": 57
                        }
                      },
                      "leadingComments": [
                        {
                          "type": "Block",
                          "value": "*\r\n\t\t * Indicates whether the Typed Array feature is supported.\r\n\t\t *\r\n\t\t * @type {Boolean}\r\n\t\t ",
                          "range": [
                            242,
                            342
                          ],
                          "loc": {
                            "start": {
                              "line": 17,
                              "column": 2
                            },
                            "end": {
                              "line": 21,
                              "column": 5
                            }
                          }
                        }
                      ]
                    }
                  ],
                  "range": [
                    208,
                    409
                  ],
                  "loc": {
                    "start": {
                      "line": 13,
                      "column": 15
                    },
                    "end": {
                      "line": 25,
                      "column": 2
                    }
                  }
                },
                "generator": false,
                "expression": false,
                "range": [
                  205,
                  409
                ],
                "loc": {
                  "start": {
                    "line": 13,
                    "column": 12
                  },
                  "end": {
                    "line": 25,
                    "column": 2
                  }
                }
              },
              "kind": "constructor",
              "computed": false,
              "range": [
                194,
                409
              ],
              "loc": {
                "start": {
                  "line": 13,
                  "column": 1
                },
                "end": {
                  "line": 25,
                  "column": 2
                }
              },
              "leadingComments": [
                {
                  "type": "Block",
                  "value": "*\r\n\t * Constructs a new Typed Array feature.\r\n\t ",
                  "range": [
                    137,
                    189
                  ],
                  "loc": {
                    "start": {
                      "line": 9,
                      "column": 1
                    },
                    "end": {
                      "line": 11,
                      "column": 4
                    }
                  }
                }
              ],
              "static": false
            }
          ],
          "range": [
            131,
            414
          ],
          "loc": {
            "start": {
              "line": 7,
              "column": 47
            },
            "end": {
              "line": 27,
              "column": 1
            }
          }
        },
        "range": [
          91,
          414
        ],
        "loc": {
          "start": {
            "line": 7,
            "column": 7
          },
          "end": {
            "line": 27,
            "column": 1
          }
        },
        "leadingComments": [
          {
            "type": "Block",
            "value": "*\r\n * The Typed Array feature.\r\n ",
            "range": [
              43,
              80
            ],
            "loc": {
              "start": {
                "line": 3,
                "column": 0
              },
              "end": {
                "line": 5,
                "column": 3
              }
            }
          }
        ],
        "trailingComments": []
      },
      "specifiers": [],
      "source": null,
      "range": [
        84,
        414
      ],
      "loc": {
        "start": {
          "line": 7,
          "column": 0
        },
        "end": {
          "line": 27,
          "column": 1
        }
      },
      "leadingComments": [
        {
          "type": "Block",
          "value": "*\r\n * The Typed Array feature.\r\n ",
          "range": [
            43,
            80
          ],
          "loc": {
            "start": {
              "line": 3,
              "column": 0
            },
            "end": {
              "line": 5,
              "column": 3
            }
          }
        }
      ]
    }
  ],
  "sourceType": "module",
  "range": [
    0,
    414
  ],
  "loc": {
    "start": {
      "line": 1,
      "column": 0
    },
    "end": {
      "line": 27,
      "column": 1
    }
  },
  "comments": [
    {
      "type": "Block",
      "value": "*\r\n * The Typed Array feature.\r\n ",
      "range": [
        43,
        80
      ],
      "loc": {
        "start": {
          "line": 3,
          "column": 0
        },
        "end": {
          "line": 5,
          "column": 3
        }
      }
    },
    {
      "type": "Block",
      "value": "*\r\n\t * Constructs a new Typed Array feature.\r\n\t ",
      "range": [
        137,
        189
      ],
      "loc": {
        "start": {
          "line": 9,
          "column": 1
        },
        "end": {
          "line": 11,
          "column": 4
        }
      }
    },
    {
      "type": "Block",
      "value": "*\r\n\t\t * Indicates whether the Typed Array feature is supported.\r\n\t\t *\r\n\t\t * @type {Boolean}\r\n\t\t ",
      "range": [
        242,
        342
      ],
      "loc": {
        "start": {
          "line": 17,
          "column": 2
        },
        "end": {
          "line": 21,
          "column": 5
        }
      }
    }
  ]
}